cloud/__init__.py
cloud/vcd/__init__.py
cloud/vcd/client.py
cloud/vcd/org.py
cloud/vcd/vapp.py
cloud/vcd/vdc.py
cloud/vcd/vm.py
clouddirector-0.0.3.dist-info/METADATA
clouddirector-0.0.3.dist-info/WHEEL
clouddirector-0.0.3.dist-info/top_level.txt
clouddirector-0.0.3.dist-info/RECORD
